ansible_executor.py
app_deployer.py
app_registry.py
cli.py
job_executor.py
job_log_manager.py
job_manager.py
security_utils.py
server_setup.py
ssh_manager.py
storage.py
api/__init__.py
api/background.py
api/dependencies.py
api/server.py
api/models/__init__.py
api/models/app.py
api/models/common.py
api/models/config.py
api/models/job.py
api/models/provider.py
api/models/remote_exec.py
api/models/secrets.py
api/models/server.py
api/models/state.py
api/routes/__init__.py
api/routes/apps.py
api/routes/jobs.py
api/routes/providers.py
api/routes/secrets.py
api/routes/servers.py
api/routes/state.py
api/routes/system.py
integrations/__init__.py
integrations/cloudflare.py
integrations/portainer.py
job_executors/__init__.py
job_executors/app_executors.py
job_executors/infrastructure_executors.py
job_executors/remote_exec_executor.py
job_executors/server_executors.py
livchat_setup-0.2.7.dist-info/licenses/LICENSE
orchestrator/__init__.py
orchestrator/core.py
orchestrator/deployment_manager.py
orchestrator/dns_manager.py
orchestrator/provider_manager.py
orchestrator/server_manager.py
providers/__init__.py
providers/base.py
providers/hetzner.py
security/__init__.py
security/command_validator.py
livchat_setup-0.2.7.dist-info/METADATA
livchat_setup-0.2.7.dist-info/WHEEL
livchat_setup-0.2.7.dist-info/entry_points.txt
livchat_setup-0.2.7.dist-info/top_level.txt
livchat_setup-0.2.7.dist-info/RECORD
